{
"type": "FeatureCollection",
"name": "assemblyPoints",
"crs": { "type": "name", "properties": { "name": "urn:ogc:def:crs:OGC:1.3:CRS84" } },
"features": [
{ "type": "Feature", "properties": { "NUMBER": 1, "DISTRICT": 1, "AREA": "UNICEF warehouse" }, "geometry": { "type": "Point", "coordinates": [ 36.3210056911, 32.3043439956 ] } },
{ "type": "Feature", "properties": { "NUMBER": 2, "DISTRICT": 3, "AREA": "The UNHCR Registration Facility" }, "geometry": { "type": "Point", "coordinates": [ 36.3232220002, 32.3036640002 ] } },
{ "type": "Feature", "properties": { "NUMBER": 3, "DISTRICT": 3, "AREA": "Rear area of the UN Admin area (Base Camp)" }, "geometry": { "type": "Point", "coordinates": [ 36.3277640001, 32.3022060004 ] } },
{ "type": "Feature", "properties": { "NUMBER": 4, "DISTRICT": 6, "AREA": "NRC Distribution Compound" }, "geometry": { "type": "Point", "coordinates": [ 36.3386920004, 32.2980749996 ] } },
{ "type": "Feature", "properties": { "NUMBER": 5, "DISTRICT": 5, "AREA": "KSA Hospital" }, "geometry": { "type": "Point", "coordinates": [ 36.330531, 32.2923170003 ] } },
{ "type": "Feature", "properties": { "NUMBER": 6, "DISTRICT": 8, "AREA": "Multi-Activity Center for Girls, MAC 4" }, "geometry": { "type": "Point", "coordinates": [ 36.3409925939, 32.2876690243 ] } },
{ "type": "Feature", "properties": { "NUMBER": 7, "DISTRICT": 9, "AREA": "ACTED Community" }, "geometry": { "type": "Point", "coordinates": [ 36.3306096691, 32.2858232701 ] } },
{ "type": "Feature", "properties": { "NUMBER": 8, "DISTRICT": 10, "AREA": "ACTED Site Office" }, "geometry": { "type": "Point", "coordinates": [ 36.325552346, 32.2879426691 ] } },
{ "type": "Feature", "properties": { "NUMBER": 9, "DISTRICT": 11, "AREA": "ACTED Lemon Center " }, "geometry": { "type": "Point", "coordinates": [ 36.3203642425, 32.2905405596 ] } },
{ "type": "Feature", "properties": { "NUMBER": 10, "DISTRICT": 12, "AREA": "IMC Empowerment Center" }, "geometry": { "type": "Point", "coordinates": [ 36.3121389999, 32.2942280003 ] } },
{ "type": "Feature", "properties": { "NUMBER": 11, "DISTRICT": 4, "AREA": "WFP Food Distribution Compound" }, "geometry": { "type": "Point", "coordinates": [ 36.3199640001, 32.2979690002 ] } }
]
}
